stackprinter/__init__.py
stackprinter/colorschemes.py
stackprinter/extraction.py
stackprinter/formatting.py
stackprinter/frame_formatting.py
stackprinter/prettyprinting.py
stackprinter/source_inspection.py
stackprinter/tracing.py
stackprinter/utils.py
stackprinter-0.2.11.dist-info/LICENSE.txt
stackprinter-0.2.11.dist-info/METADATA
stackprinter-0.2.11.dist-info/WHEEL
stackprinter-0.2.11.dist-info/top_level.txt
stackprinter-0.2.11.dist-info/RECORD
