Metadata-Version: 2.1
Name: stackprinter
Version: 0.2.11
Summary: Debug-friendly stack traces, with variable values and semantic highlighting
Home-page: https://github.com/cknd/stackprinter
Author: cknd
Author-email: ck-github@mailbox.org
Classifier: Programming Language :: Python :: 3
Classifier: License :: OSI Approved :: MIT License
Classifier: Operating System :: OS Independent
Requires-Python: >=3.4
License-File: LICENSE.txt
